eodc_connect/__init__.py
eodc_connect/auth.py
eodc_connect/dask.py
eodc_connect/settings.py
eodc_connect-0.1.3.dist-info/METADATA
eodc_connect-0.1.3.dist-info/WHEEL
eodc_connect-0.1.3.dist-info/RECORD
