Metadata-Version: 2.4
Name: eodc-connect
Version: 0.1.3
Summary: Python library for authentication towards EODC services
Author: Gerald Irsiegler
Author-email: gerald.irsiegler@eodc.eu
Maintainer: EODC Staff
Maintainer-email: support@eodc.eu
Requires-Python: >=3.10,<3.13
Classifier: Development Status :: 1 - Planning
Classifier: Intended Audience :: Developers
Classifier: Programming Language :: Python
Classifier: Programming Language :: Python :: 3
Classifier: Programming Language :: Python :: 3.10
Classifier: Programming Language :: Python :: 3.11
Classifier: Programming Language :: Python :: 3.12
Classifier: Programming Language :: Python :: 3 :: Only
Requires-Dist: dask (==2025.7.*)
Requires-Dist: dask-gateway (==2025.4.0)
Requires-Dist: pydantic (>=2.0.1,<3.0.0)
Requires-Dist: pydantic-settings (>=2.3.4,<3.0.0)
Requires-Dist: pyjwt[crypto] (>=2.8.0,<3.0.0)
Requires-Dist: requests (>=2.32.5,<3.0.0)
Project-URL: Repository, https://github.com/eodcgmbh/eodc-connect
